vital_statistics_jp/__init__.py
vital_statistics_jp/prompt.py
vital_statistics_jp-0.1.7.dist-info/WHEEL
vital_statistics_jp-0.1.7.dist-info/METADATA
vital_statistics_jp-0.1.7.dist-info/RECORD
