Metadata-Version: 2.1
Name: vital-statistics-jp
Version: 0.1.7
Summary: vital statistics downloader
Home-page: https://github.com/u-masao/vital_statistics_jp
Author: u-masao
Author-email: 4973920+u-masao@users.noreply.github.com
Requires-Python: >=3.7.1,<4.0.0
Classifier: Programming Language :: Python :: 3
Classifier: Programming Language :: Python :: 3.10
Classifier: Programming Language :: Python :: 3.8
Classifier: Programming Language :: Python :: 3.9
Requires-Dist: openpyxl (>=3.0.9,<4.0.0)
Requires-Dist: pandas (>=1.1)
Requires-Dist: xlrd (>=2.0.1,<3.0.0)
Project-URL: Repository, https://github.com/u-masao/vital_statistics_jp
